apat_frame/.DS_Store
apat_frame/__init__.py
apat_frame/plugins/.DS_Store
apat_frame/plugins/__init__.py
apat_frame/plugins/allure.7z
apat_frame/plugins/appium.7z
apat_frame/test_utils/.DS_Store
apat_frame/test_utils/__init__.py
apat_frame/test_utils/assertinfo/assertinfo.json
apat_frame/test_utils/dbconnect/__init__.py
apat_frame/test_utils/dbconnect/async_dbddl.py
apat_frame/test_utils/dbconnect/db.json
apat_frame/test_utils/dbconnect/sync_dbddl.py
apat_frame/test_utils/dbconnect/async_dbsetting/__init__.py
apat_frame/test_utils/dbconnect/async_dbsetting/app1/__init__.py
apat_frame/test_utils/dbconnect/async_dbsetting/app1/testcaseModel.py
apat_frame/test_utils/dbconnect/sync_dbsetting/__init__.py
apat_frame/test_utils/dbconnect/sync_dbsetting/app1/__init__.py
apat_frame/test_utils/dbconnect/sync_dbsetting/app1/testcaseModel.py
apat_frame/test_utils/log/__init__.py
apat_frame/test_utils/log/request/request_log.json
apat_frame/test_utils/testreport/__init__.py
apat_frame/test_utils/tools/RequestAndResponse.py
apat_frame/test_utils/tools/__init__.py
apat_frame/test_utils/tools/commonpath.py
apat_frame/test_utils/tools/compare.py
apat_frame/test_utils/tools/setup.py
apat_frame/test_utils/tools/zip.py
apat_frame-1.0.14.dist-info/METADATA
apat_frame-1.0.14.dist-info/WHEEL
apat_frame-1.0.14.dist-info/top_level.txt
apat_frame-1.0.14.dist-info/RECORD
