Metadata-Version: 2.1
Name: apat_frame
Version: 1.0.14
Summary: 本库旨在完成全流程自动化测试，包括webUI自动化测试，移动端自动化测试，接口自动化测试，自动化测试报告生成，自动化测试用例管理，自动化测试数据管理，自动化测试用例执行，自动化测试用例执行结果展示，自动化测试用例执行结果统计，自动化测试用例执行结果导出，自动化测试用例执行结果导入，自动化测试用例执行结果对比，自动化测试用例执行结果对比结果展示，自动化测试用例执行结果对比结果导出，自动化测试用例执行结果对比结果导入，自动化测试用例执行结果对比结果对比，自动化测试用例执行
Home-page: 
Author: zhangyuze
Author-email: zhangyuze1113@163.com
License: MIT
Requires-Dist: aiohttp ==3.9.5
Requires-Dist: allure-pytest ==2.13.5
Requires-Dist: setuptools ==70.0.0
Requires-Dist: Appium-Python-Client ==4.0.0
Requires-Dist: playwright ==1.44.0
Requires-Dist: pytest ==8.2.2
Requires-Dist: tortoise-orm ==0.21.3
Requires-Dist: aiosqlite ==0.17.0
Requires-Dist: asyncpg ==0.29.0
Requires-Dist: aiomysql ==0.2.0
Requires-Dist: pillow ==10.3.0
Requires-Dist: aiofiles ==23.2.1
Requires-Dist: numpy ==1.26.4
Requires-Dist: py7zr ==0.21.0
Requires-Dist: pytest-asyncio
Requires-Dist: sqlalchemy ==2.0.31
Requires-Dist: mysql-connector-python ==8.4.0
Requires-Dist: pyodbc ==5.1.0
Requires-Dist: psycopg2-binary ==2.9.9
